infinibrowser/__init__.py
infinibrowser/client.py
infinibrowser/exceptions.py
infinibrowser/py.typed
infinibrowser/types/__init__.py
infinibrowser/types/items.py
infinibrowser/types/search.py
infinibrowser-0.1.3.dist-info/METADATA
infinibrowser-0.1.3.dist-info/WHEEL
infinibrowser-0.1.3.dist-info/licenses/LICENSE
infinibrowser-0.1.3.dist-info/RECORD
