Metadata-Version: 2.4
Name: infinibrowser
Version: 0.1.3
Summary: A simple API wrapper for infinibrowser.wiki
Project-URL: Source, https://github.com/gameroman/infinibrowser
Author-email: GameRoMan <gameromandev@gmail.com>
License: MIT
License-File: LICENSE
Keywords: api,browser,client,craft,database,infinibrowser,infinite,tools
Classifier: License :: OSI Approved :: MIT License
Classifier: Programming Language :: Python :: 3
Classifier: Programming Language :: Python :: 3.10
Classifier: Programming Language :: Python :: 3.11
Classifier: Programming Language :: Python :: 3.12
Classifier: Programming Language :: Python :: 3.13
Requires-Python: >=3.10
Requires-Dist: pydantic>=2.11.7
